{
  "id": "azore-api-environment",
  "name": "Azore API Environment",
  "values": [
    {
      "key": "base_url",
      "value": "http://localhost:8800",
      "type": "default",
      "enabled": true
    },
    {
      "key": "api_key",
      "value": "354b889afef6398ebaa099a4c0dbc01281d5857412141ea6cc18e579b0ea7e38",
      "type": "secret",
      "enabled": true
    },
    {
      "key": "access_token",
      "value": "",
      "type": "secret",
      "enabled": true
    },
    {
      "key": "refresh_token",
      "value": "",
      "type": "secret",
      "enabled": true
    },
    {
      "key": "reset_token",
      "value": "",
      "type": "default",
      "enabled": true
    },
    {
      "key": "client_id",
      "value": "",
      "type": "default",
      "enabled": true
    },
    {
      "key": "user_id",
      "value": "",
      "type": "default",
      "enabled": true
    },
    {
      "key": "email",
      "value": "ivan.alberton@navi.inf.br",
      "type": "default",
      "enabled": true
    },
    {
      "key": "password",
      "value": "N@vi@2025",
      "type": "secret",
      "enabled": true
    },
    {
      "key": "user_name",
      "value": "Juan Silveira",
      "type": "default",
      "enabled": true
    },
    {
      "key": "cpf",
      "value": "05607112985",
      "type": "default",
      "enabled": true
    },
    {
      "key": "wallet_address",
      "value": "0x1234567890123456789012345678901234567890",
      "type": "default",
      "enabled": true
    },
    {
      "key": "client_name",
      "value": "Navi",
      "type": "default",
      "enabled": true
    },
    {
      "key": "api_key_name",
      "value": "Azore",
      "type": "default",
      "enabled": true
    },
    {
      "key": "api_key_id",
      "value": "",
      "type": "default",
      "enabled": true
    },
    {
      "key": "page",
      "value": "1",
      "type": "default",
      "enabled": true
    },
    {
      "key": "limit",
      "value": "10",
      "type": "default",
      "enabled": true
    },
    {
      "key": "network",
      "value": "testnet",
      "type": "default",
      "enabled": true
    },
    {
      "key": "job_id",
      "value": "",
      "type": "default",
      "enabled": true
    },
    {
      "key": "queue_name",
      "value": "blockchain-transactions",
      "type": "default",
      "enabled": true
    },
    {
      "key": "contract_address",
      "value": "0x0A8c73967e4Eee8ffA06484C3fBf65E6Ae3b9804",
      "type": "default",
      "enabled": true
    },
    {
      "key": "contract_abi",
      "value": "[]",
      "type": "default",
      "enabled": true
    },
    {
      "key": "function_name",
      "value": "mint",
      "type": "default",
      "enabled": true
    },
    {
      "key": "role",
      "value": "minter",
      "type": "default",
      "enabled": true
    },
    {
      "key": "user_address",
      "value": "",
      "type": "default",
      "enabled": true
    },
    {
      "key": "admin_public_key",
      "value": "0x5528C065931f523CA9F3a6e49a911896fb1D2e6f",
      "type": "default",
      "enabled": true
    },
    {
      "key": "block_number",
      "value": "0",
      "type": "default",
      "enabled": true
    },
    {
      "key": "transaction_hash",
      "value": "0x1234567890123456789012345678901234567890123456789012345678901234",
      "type": "default",
      "enabled": true
    },
    {
      "key": "token_address",
      "value": "0x1234567890123456789012345678901234567890",
      "type": "default",
      "enabled": true
    },
    {
      "key": "amount",
      "value": "1000000000000000000",
      "type": "default",
      "enabled": true
    },
    {
      "key": "to_address",
      "value": "0x1234567890123456789012345678901234567890",
      "type": "default",
      "enabled": true
    },
    {
      "key": "from_address",
      "value": "0x1234567890123456789012345678901234567890",
      "type": "default",
      "enabled": true
    },
    {
      "key": "gas_payer",
      "value": "0x5528C065931f523CA9F3a6e49a911896fb1D2e6f",
      "type": "default",
      "enabled": true
    },
    {
      "key": "event_name",
      "value": "Transfer",
      "type": "default",
      "enabled": true
    },
    {
      "key": "from_block",
      "value": "0",
      "type": "default",
      "enabled": true
    },
    {
      "key": "to_block",
      "value": "latest",
      "type": "default",
      "enabled": true
    },
    {
      "key": "stake_id",
      "value": "",
      "type": "default",
      "enabled": true
    },
    {
      "key": "start_date",
      "value": "2024-01-01",
      "type": "default",
      "enabled": true
    },
    {
      "key": "end_date",
      "value": "2024-12-31",
      "type": "default",
      "enabled": true
    },
    {
      "key": "log_id",
      "value": "",
      "type": "default",
      "enabled": true
    },
    {
      "key": "status_code",
      "value": "200",
      "type": "default",
      "enabled": true
    },
    {
      "key": "method",
      "value": "GET",
      "type": "default",
      "enabled": true
    },
    {
      "key": "endpoint",
      "value": "/api/health",
      "type": "default",
      "enabled": true
    }
  ]
} 